jsgprogressbar/__init__.py
jsgprogressbar/progressbar.py
jsgprogressbar/test.py
jsgprogressbar/__pycache__/progressbar.cpython-311.pyc
jsgprogressbar-1.0.4.dist-info/LICENSE
jsgprogressbar-1.0.4.dist-info/METADATA
jsgprogressbar-1.0.4.dist-info/WHEEL
jsgprogressbar-1.0.4.dist-info/top_level.txt
jsgprogressbar-1.0.4.dist-info/RECORD
