Metadata-Version: 2.1
Name: jsgprogressbar
Version: 1.0.4
Summary: A function that makes a progressbar for your loops
Author: Juan Santos Gomez
Author-email: Juan Santos Gomez <juansantosgomez@protonmail.com>
Project-URL: Homepage, https://github.com/JuanSantosGomez/loopprogress
Classifier: Programming Language :: Python :: 3
Classifier: License :: OSI Approved :: MIT License
Classifier: Operating System :: OS Independent
Requires-Python: >=3.3
License-File: LICENSE
